{
    "Calculator": {
        "name": "Calculator",
        "icon": "https://raw.githubusercontent.com/fwldom/Calculator_Web.github.io/main/icon.png",
        "directory": "./apps/Calculator",
        "type": "app",
        "description": "A simple calculator app",
        "version": "1.0.0",
        "author": "Fwldom",
        "website": "https://github.com/Fwldom/Calculator",
        "license": "MIT",
        "files": ["https://raw.githubusercontent.com/fwldom/Calculator_Web.github.io/main/index.js", "https://raw.githubusercontent.com/fwldom/Calculator_Web.github.io/main/index.html", "https://raw.githubusercontent.com/fwldom/Calculator_Web.github.io/main/style.css", "https://raw.githubusercontent.com/fwldom/Calculator_Web.github.io/main/icon.png"]
    },
    "Freedom Player": {
        "name": "Freedom Player",
        "icon": "https://raw.githubusercontent.com/Freedom-Guard/Freedom-Guard/main/plus/apps/Freedom_Player/Freedom_Player.png",
        "directory": "./apps/Freedom Player",
        "type": "app",
        "description": "A Player for music",
        "version": "1.0.0",
        "author": "Freedom-Guard",
        "website": "https://github.com/Freedom-Guard/Freedom-Guard",
        "license": "MIT",
        "files": ["https://raw.githubusercontent.com/Freedom-Guard/Freedom-Guard/main/plus/apps/Freedom Player/index.js",
        "https://raw.githubusercontent.com/Freedom-Guard/Freedom-Guard/main/plus/apps/Freedom Player/index.html",
        "https://raw.githubusercontent.com/Freedom-Guard/Freedom-Guard/main/plus/apps/Freedom Player/style.css",
        "https://raw.githubusercontent.com/Freedom-Guard/Freedom-Guard/main/plus/apps/Freedom Player/Freedom_Player.png"]
    }
}
